examples/__init__.py
examples/abc_sdl.py
examples/cs_sdl.py
examples/de_hybrid.py
examples/de_sdl.py
examples/de_sdl_tune.py
examples/firefly_sdl.py
examples/gwo_sdl.py
examples/jaya_sdl.py
examples/pso_api.py
examples/pso_api_tune.py
examples/pso_sdl.py
examples/sca_sdl.py
examples/tlbo_sdl.py
examples/wo_sdl.py
swarmist/__init__.py
swarmist/initialization.py
swarmist/recombination.py
swarmist/search.py
swarmist/space.py
swarmist/strategy.py
swarmist/tune.py
swarmist/update.py
swarmist/core/__init__.py
swarmist/core/dictionary.py
swarmist/core/errors.py
swarmist/core/evaluator.py
swarmist/core/executor.py
swarmist/core/info.py
swarmist/core/population.py
swarmist/core/random.py
swarmist/core/references.py
swarmist/sdl/__init__.py
swarmist/sdl/grammar.py
swarmist/sdl/parser.py
swarmist/sdl/sdl.py
swarmist/sdl/expressions/__init__.py
swarmist/sdl/expressions/expressions.py
swarmist/sdl/expressions/function_expressions.py
swarmist/sdl/expressions/init_expressions.py
swarmist/sdl/expressions/math_expressions.py
swarmist/sdl/expressions/random_expressions.py
swarmist/sdl/expressions/references_expressions.py
swarmist/sdl/expressions/space_expressions.py
swarmist/sdl/expressions/update_expressions.py
swarmist/utils/__init__.py
swarmist/utils/benchmark.py
swarmist-0.0.6.dist-info/LICENSE
swarmist-0.0.6.dist-info/METADATA
swarmist-0.0.6.dist-info/WHEEL
swarmist-0.0.6.dist-info/top_level.txt
swarmist-0.0.6.dist-info/RECORD
