Metadata-Version: 2.1
Name: swarmist
Version: 0.0.6
Summary: A DSL for building metaheuristics
Home-page: https://github.com/kafm/swarmist
Author: Kevin Martins
License: MIT
Keywords: swarmist,metaheuristics,optimization,dsl
Classifier: Development Status :: 2 - Pre-Alpha
Classifier: Intended Audience :: Developers
Classifier: Intended Audience :: Education
Classifier: Intended Audience :: Information Technology
Classifier: Intended Audience :: Science/Research
Classifier: Topic :: Scientific/Engineering
Classifier: Topic :: Scientific/Engineering :: Mathematics
Classifier: Topic :: Scientific/Engineering :: Artificial Intelligence
Classifier: Topic :: Software Development
Classifier: Topic :: Software Development :: Libraries
Classifier: Topic :: Software Development :: Libraries :: Python Modules
Classifier: Programming Language :: Python :: 3.10
Classifier: Programming Language :: Python :: 3.11
Requires-Python: >= 3.10
License-File: LICENSE
Requires-Dist: numpy
Requires-Dist: scipy (>=1.10)
Requires-Dist: lark (>=1.1)
Requires-Dist: PyMonad (>=2.4)
Requires-Dist: optuna (>=3.2)
